aiconfig_extension_groq/__init__.py
aiconfig_extension_groq/groq.py
aiconfig_extension_groq-0.0.2.dist-info/LICENSE
aiconfig_extension_groq-0.0.2.dist-info/METADATA
aiconfig_extension_groq-0.0.2.dist-info/WHEEL
aiconfig_extension_groq-0.0.2.dist-info/top_level.txt
aiconfig_extension_groq-0.0.2.dist-info/RECORD
