Metadata-Version: 2.1
Name: aiconfig_extension_groq
Version: 0.0.2
Summary: An extension for using the Groq client wrapper with AIConfig.
Author: LastMile AI
Author-email: Rossdan Craig <rossdan@lastmileai.dev>, Ankush Pala <ankush@lastmileai.dev>
Project-URL: Homepage, https://github.com/lastmile-ai/aiconfig/
Project-URL: Issues, https://github.com/lastmile-ai/aiconfig/issues
Classifier: Programming Language :: Python :: 3
Classifier: License :: OSI Approved :: MIT License
Classifier: Operating System :: OS Independent
Requires-Python: >=3.10
License-File: LICENSE
Requires-Dist: python-aiconfig
Requires-Dist: groq
